Metadata-Version: 2.4
Name: crawlfish
Version: 0.1.5
Summary: An easy to use web crawling library with handy functions for exploring whole websites or single webpages , dynamic element searching , generic web scraping  and  more . It also has helpful shortcut functions for bs4 , requests and selenium . 
Home-page: https://github.com/victhepythonista/crawlfish
Author: Victor Kipkemboi
Author-email: scriptilapia@gmail.com
Project-URL: Bug Tracker, https://github.com/victhepythonista/crawlfish/issues
Classifier: Programming Language :: Python :: 3
Classifier: License :: OSI Approved :: MIT License
Requires-Python: >=3.6
License-File: LICENSE
Requires-Dist: art
Requires-Dist: ascii-magic
Requires-Dist: openpyxl
Requires-Dist: selenium
Requires-Dist: requests
Requires-Dist: tabulate
Requires-Dist: tldextract
Requires-Dist: bs4
Requires-Dist: tqdm
Dynamic: author
Dynamic: author-email
Dynamic: classifier
Dynamic: description
Dynamic: description-content-type
Dynamic: home-page
Dynamic: license-file
Dynamic: project-url
Dynamic: requires-dist
Dynamic: requires-python
Dynamic: summary
